nbgitpuller_downloader_dropbox/__init__.py
nbgitpuller_downloader_dropbox/dropbox_downloader.py
nbgitpuller_downloader_dropbox-0.1.0a1.dist-info/LICENSE
nbgitpuller_downloader_dropbox-0.1.0a1.dist-info/METADATA
nbgitpuller_downloader_dropbox-0.1.0a1.dist-info/WHEEL
nbgitpuller_downloader_dropbox-0.1.0a1.dist-info/entry_points.txt
nbgitpuller_downloader_dropbox-0.1.0a1.dist-info/top_level.txt
nbgitpuller_downloader_dropbox-0.1.0a1.dist-info/RECORD
